pyowm/__init__.py
pyowm/config.py
pyowm/constants.py
pyowm/owm.py
pyowm/agroapi10/__init__.py
pyowm/agroapi10/agro_manager.py
pyowm/agroapi10/enums.py
pyowm/agroapi10/imagery.py
pyowm/agroapi10/polygon.py
pyowm/agroapi10/search.py
pyowm/agroapi10/soil.py
pyowm/agroapi10/uris.py
pyowm/airpollutionapi30/__init__.py
pyowm/airpollutionapi30/airpollution_client.py
pyowm/airpollutionapi30/airpollution_manager.py
pyowm/airpollutionapi30/airstatus.py
pyowm/airpollutionapi30/coindex.py
pyowm/airpollutionapi30/no2index.py
pyowm/airpollutionapi30/ozone.py
pyowm/airpollutionapi30/so2index.py
pyowm/airpollutionapi30/uris.py
pyowm/alertapi30/__init__.py
pyowm/alertapi30/alert.py
pyowm/alertapi30/alert_manager.py
pyowm/alertapi30/condition.py
pyowm/alertapi30/enums.py
pyowm/alertapi30/trigger.py
pyowm/alertapi30/uris.py
pyowm/commons/__init__.py
pyowm/commons/cityidregistry.py
pyowm/commons/databoxes.py
pyowm/commons/enums.py
pyowm/commons/exceptions.py
pyowm/commons/http_client.py
pyowm/commons/image.py
pyowm/commons/tile.py
pyowm/commons/uris.py
pyowm/commons/cityids/__init__.py
pyowm/commons/cityids/cities.db.bz2
pyowm/geocodingapi10/__init__.py
pyowm/geocodingapi10/geocoding_manager.py
pyowm/stationsapi30/__init__.py
pyowm/stationsapi30/buffer.py
pyowm/stationsapi30/measurement.py
pyowm/stationsapi30/persistence_backend.py
pyowm/stationsapi30/station.py
pyowm/stationsapi30/stations_manager.py
pyowm/stationsapi30/uris.py
pyowm/tiles/__init__.py
pyowm/tiles/enums.py
pyowm/tiles/tile_manager.py
pyowm/tiles/uris.py
pyowm/utils/__init__.py
pyowm/utils/config.py
pyowm/utils/decorators.py
pyowm/utils/formatting.py
pyowm/utils/geo.py
pyowm/utils/measurables.py
pyowm/utils/strings.py
pyowm/utils/timestamps.py
pyowm/utils/weather.py
pyowm/uvindexapi30/__init__.py
pyowm/uvindexapi30/uris.py
pyowm/uvindexapi30/uv_client.py
pyowm/uvindexapi30/uvindex.py
pyowm/uvindexapi30/uvindex_manager.py
pyowm/weatherapi30/__init__.py
pyowm/weatherapi30/forecast.py
pyowm/weatherapi30/forecaster.py
pyowm-3.4.0.dist-info/licenses/LICENSE
pyowm-3.4.0.dist-info/METADATA
pyowm-3.4.0.dist-info/WHEEL
pyowm-3.4.0.dist-info/top_level.txt
pyowm-3.4.0.dist-info/RECORD
