Metadata-Version: 2.4
Name: pyowm
Version: 3.4.0
Summary: A Python wrapper around OpenWeatherMap web APIs
Home-page: https://github.com/csparpa/pyowm
Author: Claudio Sparpaglione
Author-email: csparpa@gmail.com
License: MIT
Keywords: openweathermap web api client weather forecast uv alerting owm pollution meteostation agro agriculture
Classifier: License :: OSI Approved :: MIT License
Classifier: Programming Language :: Python
Classifier: Programming Language :: Python :: 3.8
Classifier: Programming Language :: Python :: 3.9
Classifier: Programming Language :: Python :: 3.10
Classifier: Programming Language :: Python :: 3.11
Classifier: Programming Language :: Python :: 3.12
Classifier: Programming Language :: Python :: 3.13
Classifier: Natural Language :: English
Classifier: Operating System :: OS Independent
Classifier: Development Status :: 5 - Production/Stable
Classifier: Intended Audience :: Developers
Classifier: Topic :: Software Development :: Libraries
Requires-Python: >=3.8
License-File: LICENSE
Requires-Dist: requests<3,>=2.20.0
Requires-Dist: geojson<4,>=2.3.0
Requires-Dist: PySocks<2,>=1.7.1
Requires-Dist: requests[socks]
Dynamic: author
Dynamic: author-email
Dynamic: classifier
Dynamic: description
Dynamic: description-content-type
Dynamic: home-page
Dynamic: keywords
Dynamic: license
Dynamic: license-file
Dynamic: requires-dist
Dynamic: requires-python
Dynamic: summary
